orbital_elements/__init__.py
orbital_elements/__main__.py
orbital_elements/orbital_graph.py
orbital_elements/tle.py
orbital_elements-0.0.1.dist-info/METADATA
orbital_elements-0.0.1.dist-info/WHEEL
orbital_elements-0.0.1.dist-info/entry_points.txt
orbital_elements-0.0.1.dist-info/top_level.txt
orbital_elements-0.0.1.dist-info/RECORD
