Metadata-Version: 2.1
Name: orbital-elements
Version: 0.0.1
Summary: A simple utility for calculating and plotting orbits from TLE's
Home-page: https://github.com/dmitri-mcguckin/python3-orbital-elements
Author: Dmitri McGuckin
License: GPL-3.0
Platform: UNKNOWN
Classifier: Programming Language :: Python :: 3
Classifier: License :: OSI Approved :: GNU General Public License v3 (GPLv3)
Classifier: Operating System :: OS Independent
Classifier: Topic :: Scientific/Engineering :: Information Analysis
Classifier: Topic :: Software Development :: User Interfaces
Requires-Python: >=3.8.5
Requires-Dist: numpy
Requires-Dist: pytz
Requires-Dist: datetime2
Requires-Dist: matplotlib
Requires-Dist: ConfigArgParse
Provides-Extra: dev
Requires-Dist: setuptools ; extra == 'dev'
Requires-Dist: wheel ; extra == 'dev'
Requires-Dist: pytest ; extra == 'dev'
Requires-Dist: flake8 ; extra == 'dev'
Requires-Dist: twine ; extra == 'dev'
Requires-Dist: sphinx ; extra == 'dev'
Requires-Dist: sphinx-rtd-theme ; extra == 'dev'
Requires-Dist: python-can ; extra == 'dev'
